cursofiap/__init__.py
cursofiap/core.py
exercicios_bombz80-1.1.0.dist-info/METADATA
exercicios_bombz80-1.1.0.dist-info/WHEEL
exercicios_bombz80-1.1.0.dist-info/top_level.txt
exercicios_bombz80-1.1.0.dist-info/RECORD
